broadcaster/__init__.py
broadcaster/_base.py
broadcaster/_backends/__init__.py
broadcaster/_backends/base.py
broadcaster/_backends/kafka.py
broadcaster/_backends/memory.py
broadcaster/_backends/postgres.py
broadcaster/_backends/redis.py
broadcaster_noteable-0.2.1.dist-info/METADATA
broadcaster_noteable-0.2.1.dist-info/WHEEL
broadcaster_noteable-0.2.1.dist-info/top_level.txt
broadcaster_noteable-0.2.1.dist-info/RECORD
