Metadata-Version: 2.1
Name: broadcaster-noteable
Version: 0.2.1
Summary: Simple broadcast channels.
Home-page: https://github.com/noteable-io/broadcaster
Author: Noteable (extending from Tom Christie)
License: BSD
Platform: UNKNOWN
Classifier: Development Status :: 3 - Alpha
Classifier: Environment :: Web Environment
Classifier: Intended Audience :: Developers
Classifier: License :: OSI Approved :: BSD License
Classifier: Operating System :: OS Independent
Classifier: Topic :: Internet :: WWW/HTTP
Classifier: Programming Language :: Python :: 3
Classifier: Programming Language :: Python :: 3.7
Classifier: Programming Language :: Python :: 3.8
Requires-Python: >=3.7
Provides-Extra: kafka
Requires-Dist: aiokafka ; extra == 'kafka'
Provides-Extra: postgres
Requires-Dist: asyncpg ; extra == 'postgres'
Provides-Extra: redis
Requires-Dist: aioredis ; extra == 'redis'
